{
  "superheroes": [
    {
      "id": 1,
      "name": "Batman",
      "alterEgo": "Bruce Wayne"
    },
    {
      "id": 2,
      "name": "Superman",
      "alterEgo": "Clark Kent"
    },
    {
      "id": 3,
      "name": "Wonder Woman",
      "alterEgo": "Princess Diana"
    }
  ],
  "friends": [
    {
      "id": 1,
      "name": "Ranju"
    },
    {
      "id": 2,
      "name": "Rohit"
    },
    {
      "id": 3,
      "name": "Umang"
    }
  ],
  "students": [
    {
      "id": 1,
      "name": "Anmol Kumar"
    },
    {
      "id": 2,
      "name": "Umang Aggarwal"
    },
    {
      "id": 3,
      "name": "Rohit Vishwakarma"
    },
    {
      "id": 4,
      "name": "Vikash chandra"
    },
    {
      "name": "Hello",
      "id": 5
    },
    {
      "name": "New dummy student",
      "id": 6
    },
    {
      "name": "sourabh",
      "id": 7
    },
    {
      "name": "sourabh",
      "id": 8
    },
    {
      "name": "sourabh",
      "id": 9
    },
    {
      "name": "sourabh",
      "id": 10
    },
    {
      "name": "sumit",
      "id": 11
    },
    {
      "name": "Rohit heheh",
      "id": 12
    },
    {
      "name": "new new data",
      "id": 13
    }
  ]
}